{
  "operationId": "activity_findEvents",
  "method": "GET",
  "path": "/activity/event",
  "summary": "Axway Get Activity Event Names",
  "requestExamples": [],
  "responseExamples": [
    {
      "status": "400",
      "contentType": "application/json",
      "name": "LOGIN_REQUIRED",
      "example": {
        "$ref": "#/components/examples/LOGIN_REQUIRED/value"
      }
    },
    {
      "status": "400",
      "contentType": "application/json",
      "name": "FORBIDDEN",
      "example": {
        "$ref": "#/components/examples/FORBIDDEN/value"
      }
    },
    {
      "status": "400",
      "contentType": "application/json",
      "name": "PARAM_INVALID",
      "example": {
        "$ref": "#/components/examples/PARAM_INVALID/value"
      }
    }
  ]
}